imurl/__init__.py
imurl/py.typed
imurl/url.py
imurl-0.2.1.dist-info/LICENSE
imurl-0.2.1.dist-info/METADATA
imurl-0.2.1.dist-info/WHEEL
imurl-0.2.1.dist-info/top_level.txt
imurl-0.2.1.dist-info/RECORD
