Metadata-Version: 2.1
Name: imurl
Version: 0.2.1
Summary: `imurl` is an immutable URL library, written in modern Python.
Home-page: https://github.com/thesketh/imurl
Author: Travis Hesketh
Author-email: travis@hesketh.scot
License: UNKNOWN
Project-URL: Bug Tracker, https://github.com/thesketh/imurl/issues
Project-URL: Documentation, https://thesketh.github.io/imurl
Platform: UNKNOWN
Classifier: Programming Language :: Python :: 3
Classifier: Programming Language :: Python :: 3.8
Classifier: License :: OSI Approved :: MIT License
Classifier: Operating System :: OS Independent
Classifier: Topic :: Software Development :: Libraries
Classifier: Typing :: Typed
Requires-Python: >=3.8
